LICENSE
MANIFEST.in
README.md
lgpl-3.0.txt
setup.cfg
setup.py
versioneer.py
src/kabaret/__init__.py
src/kabaret.blender_session.egg-info/PKG-INFO
src/kabaret.blender_session.egg-info/SOURCES.txt
src/kabaret.blender_session.egg-info/dependency_links.txt
src/kabaret.blender_session.egg-info/requires.txt
src/kabaret.blender_session.egg-info/top_level.txt
src/kabaret/blender_session/__init__.py
src/kabaret/blender_session/_version.py
src/kabaret/blender_session/session/__init__.py
src/kabaret/blender_session/session/flow_view.py
src/kabaret/blender_session/user_scripts/__init__.py
src/kabaret/blender_session/user_scripts/startup/kabaret_startup.py