Metadata-Version: 2.1
Name: kabaret.blender-session
Version: 0.0.17
Summary: A Kabaret session usable in blender to have a Flow view in 3D view tools.
Home-page: https://gitlab.com/kabaretstudio/kabaret.blender_session
Author: Damien "dee" Coureau
Author-email: kabaret-dev@googlegroups.com
License: LGPLv3+
Keywords: kabaret blender b3d pipeline dataflow workflow
Platform: UNKNOWN
Classifier: Development Status :: 3 - Alpha
Classifier: Intended Audience :: Developers
Classifier: Operating System :: OS Independent
Classifier: Programming Language :: Python :: 3.7
Classifier: License :: OSI Approved :: GNU Lesser General Public License v3 or later (LGPLv3+)
Requires-Python: >=3.7
